pJITAI/__init__.py
pJITAI/client.py
pJITAI/codes.py
pJITAI/datatypes.py
pJITAI/util.py
pJITAI-1.1.2.dist-info/LICENSE.md
pJITAI-1.1.2.dist-info/METADATA
pJITAI-1.1.2.dist-info/WHEEL
pJITAI-1.1.2.dist-info/top_level.txt
pJITAI-1.1.2.dist-info/RECORD
