Metadata-Version: 2.1
Name: pJITAI
Version: 1.1.2
Summary: The mHealth Center for Discovery, Optimization & Translation of Temporally-Precise Intervention tookbox for personalized Just-In-Time Adaptive Interventions
Author-email: mDOT Center <dev@md2k.org>
License: Copyright (c) 2022. University of Memphis, mDOT Center        
Project-URL: Homepage, https://github.com/mDOT-Center/pJITAI-python
Keywords: mHealth,mDOT,JITAI,Reinforcement Learning
Classifier: License :: OSI Approved :: BSD License
Classifier: Programming Language :: Python
Classifier: Programming Language :: Python :: 3
Requires-Python: >=3.9
License-File: LICENSE.md
Requires-Dist: typing
Requires-Dist: dataclasses
Requires-Dist: requests
Requires-Dist: responses
Provides-Extra: dev
Requires-Dist: bumpver ; extra == 'dev'
Requires-Dist: isort ; extra == 'dev'
Requires-Dist: pip-tools ; extra == 'dev'
